odoo/addons/loyalty_coupon_no_mail/README.rst
odoo/addons/loyalty_coupon_no_mail/__init__.py
odoo/addons/loyalty_coupon_no_mail/__manifest__.py
odoo/addons/loyalty_coupon_no_mail/i18n/it.po
odoo/addons/loyalty_coupon_no_mail/i18n/loyalty_coupon_no_mail.pot
odoo/addons/loyalty_coupon_no_mail/models/__init__.py
odoo/addons/loyalty_coupon_no_mail/models/loyalty_mail.py
odoo/addons/loyalty_coupon_no_mail/models/loyalty_program.py
odoo/addons/loyalty_coupon_no_mail/readme/CONTRIBUTORS.md
odoo/addons/loyalty_coupon_no_mail/readme/DESCRIPTION.md
odoo/addons/loyalty_coupon_no_mail/readme/USAGE.md
odoo/addons/loyalty_coupon_no_mail/static/description/icon.png
odoo/addons/loyalty_coupon_no_mail/static/description/index.html
odoo/addons/loyalty_coupon_no_mail/tests/__init__.py
odoo/addons/loyalty_coupon_no_mail/tests/test_loyalty_mail.py
odoo/addons/loyalty_coupon_no_mail/views/loyalty_mail_views.xml
odoo/addons/loyalty_coupon_no_mail/views/loyalty_program_views.xml
odoo_addon_loyalty_coupon_no_mail-18.0.1.0.0.4.dist-info/METADATA
odoo_addon_loyalty_coupon_no_mail-18.0.1.0.0.4.dist-info/WHEEL
odoo_addon_loyalty_coupon_no_mail-18.0.1.0.0.4.dist-info/top_level.txt
odoo_addon_loyalty_coupon_no_mail-18.0.1.0.0.4.dist-info/RECORD
